<?xml version="1.0"?>
<!DOCTYPE hibernate-mapping PUBLIC "-//Hibernate/Hibernate Mapping DTD 3.0//EN"
"http://www.hibernate.org/dtd/hibernate-mapping-3.0.dtd">
<!-- Generated 4/11/2015 10:38:46 AM by Hibernate Tools 4.3.1 -->
<hibernate-mapping>
    <class name="dto.Usuario" table="usuario" catalog="sigerbd" optimistic-lock="version">
        <id name="idUsuario" type="java.lang.Integer">
            <column name="id_usuario" />
            <generator class="identity" />
        </id>
        <many-to-one name="despacho" class="dto.Despacho" fetch="select">
            <column name="id_despacho" not-null="true" />
        </many-to-one>
        <property name="nombre" type="string">
            <column name="nombre" length="45" not-null="true" />
        </property>
        <property name="paterno" type="string">
            <column name="paterno" length="45" not-null="true" />
        </property>
        <property name="materno" type="string">
            <column name="materno" length="45" />
        </property>
        <property name="nombreLogin" type="string">
            <column name="nombre_login" length="20" not-null="true" />
        </property>
        <property name="password" type="string">
            <column name="password" length="45" not-null="true" />
        </property>
        <property name="perfil" type="int">
            <column name="perfil" not-null="true" />
        </property>
        <property name="correo" type="string">
            <column name="correo" length="50" not-null="true" />
        </property>
        <property name="imagenPerfil" type="string">
            <column name="imagen_perfil" length="30" />
        </property>
        <set name="administrativos" table="administrativo" inverse="true" lazy="true" fetch="select">
            <key>
                <column name="id_usuario" not-null="true" />
            </key>
            <one-to-many class="dto.Administrativo" />
        </set>
        <set name="gestors" table="gestor" inverse="true" lazy="true" fetch="select">
            <key>
                <column name="id_usuario" not-null="true" />
            </key>
            <one-to-many class="dto.Gestor" />
        </set>
    </class>
</hibernate-mapping>
